mms_python_client/__init__.py
mms_python_client/api_client.py
mms_python_client/configuration.py
mms_python_client/exceptions.py
mms_python_client/model_utils.py
mms_python_client/rest.py
mms_python_client/api/__init__.py
mms_python_client/api/artifacts_api.py
mms_python_client/api/auth_api.py
mms_python_client/api/commits_api.py
mms_python_client/api/elements_api.py
mms_python_client/api/groups_api.py
mms_python_client/api/mms_version_api.py
mms_python_client/api/notebooks_api.py
mms_python_client/api/orgs_api.py
mms_python_client/api/projects_api.py
mms_python_client/api/refs_api.py
mms_python_client/api/search_api.py
mms_python_client/api/views_api.py
mms_python_client/api/webhooks_api.py
mms_python_client/apis/__init__.py
mms_python_client/model/__init__.py
mms_python_client/model/basic_search_request.py
mms_python_client/model/commit.py
mms_python_client/model/commits_request.py
mms_python_client/model/commits_response.py
mms_python_client/model/documents_response.py
mms_python_client/model/element.py
mms_python_client/model/element_version.py
mms_python_client/model/elements_request.py
mms_python_client/model/elements_response.py
mms_python_client/model/elements_search_response.py
mms_python_client/model/group_response.py
mms_python_client/model/group_update_request.py
mms_python_client/model/group_update_response.py
mms_python_client/model/groups_response.py
mms_python_client/model/inline_response200.py
mms_python_client/model/jwt_authentication_request.py
mms_python_client/model/jwt_authentication_response.py
mms_python_client/model/jwt_token_validation_response.py
mms_python_client/model/mount.py
mms_python_client/model/mounts_response.py
mms_python_client/model/notebooks_request.py
mms_python_client/model/notebooks_response.py
mms_python_client/model/org.py
mms_python_client/model/organizations_request.py
mms_python_client/model/organizations_response.py
mms_python_client/model/permission.py
mms_python_client/model/permission_lookup.py
mms_python_client-4.0.18.dist-info/METADATA
mms_python_client-4.0.18.dist-info/WHEEL
mms_python_client-4.0.18.dist-info/top_level.txt
mms_python_client-4.0.18.dist-info/RECORD
